{"v":"5.7.1","ip":0,"op":5,"nm":"turtleUp_rtl.svg","mn":"{58ee1ea9-4009-472b-bcb1-3625452dad6f}","fr":3,"w":550,"h":550,"assets":[{"nm":"Composition","mn":"{c4b4a130-0e3c-42be-96a9-f32a628723a7}","fr":60,"w":512,"h":512,"id":"{c4b4a130-0e3c-42be-96a9-f32a628723a7}","layers":[{"ty":0,"ddd":0,"nm":"turtleUp_rtl.svg","mn":"{29355842-bdd8-4cf5-bf32-029ebb1fa36f}","ip":0,"op":5,"ind":1,"st":0,"sr":1,"ks":{"a":{"a":0,"k":[256.039,252.557]},"p":{"a":0,"k":[237.686,235.070]},"s":{"a":0,"k":[91.841,88.424]},"r":{"a":0,"k":-0.692},"o":{"a":0,"k":100}},"refId":"{58ee1ea9-4009-472b-bcb1-3625452dad6f}","w":550,"h":550},{"ddd":0,"ty":3,"ind":0,"st":0,"ip":0,"op":30,"nm":"Layer","mn":"{c77fedd2-7ce9-4560-8293-212456ec3beb}","ao":0,"ks":{"a":{"a":0,"k":[256,256]},"p":{"a":0,"k":[256,256]},"s":{"a":0,"k":[100,100]},"r":{"a":0,"k":0},"o":{"a":0,"k":100}}}]}],"layers":[{"ddd":0,"ty":3,"ind":2,"st":0,"ip":0,"op":5,"nm":"turtleUp_rtl.svg","mn":"{199ac604-ebb8-47bf-be60-e07163b5bf20}","ao":0,"ks":{"a":{"a":0,"k":[0,0]},"p":{"a":0,"k":[0,0]},"s":{"a":0,"k":[377.953,377.953]},"r":{"a":0,"k":0},"o":{"a":0,"k":100}}},{"ddd":0,"ty":4,"ind":3,"st":0,"ip":0,"op":5,"nm":"turtleUpRTL","mn":"{6b7b0c4f-29a4-4a72-85c3-43e3a477d8a3}","ao":0,"ks":{"a":{"a":0,"k":[0,0]},"p":{"a":0,"k":[0,0]},"s":{"a":0,"k":[100,100]},"r":{"a":0,"k":0},"o":{"a":0,"k":100}},"parent":2,"shapes":[{"ty":"gr","nm":"R_phridi","mn":"{fa59d9ce-e01a-4bb6-a4ce-1072d6a418d7}","it":[{"ty":"sh","nm":"","mn":"{76b21a81-661a-4dd3-80fd-8bb8c11416a9}","d":1,"ks":{"a":0,"k":{"c":true,"v":[[52.306,11.089],[63.098,4.872],[63.319,6.900],[52.306,11.089]],"i":[[0,0],[-1.114,-0.708],[0.695,-0.798],[4.963,-6.679]],"o":[[6.131,-10.530],[1.114,0.708],[-3.671,-3.683],[0,0]]}}},{"ty":"fl","nm":"","mn":"{57748f6e-86b5-4786-9c72-80a19b9a0ffb}","o":{"a":0,"k":100},"r":1,"c":{"a":0,"k":[0.059,0.047,0.024]}},{"ty":"st","nm":"","mn":"{c423795c-97c1-45ac-a40f-ef48eb50e053}","o":{"a":0,"k":100},"lc":2,"lj":2,"ml":4,"w":{"a":0,"k":1.115},"c":{"a":0,"k":[0.059,0.047,0.024]}},{"ty":"tr","a":{"a":0,"k":[0,0]},"p":{"a":0,"k":[0,0]},"s":{"a":0,"k":[100,100]},"r":{"a":0,"k":0},"o":{"a":0,"k":100}}]},{"ty":"gr","nm":"L_phridi","mn":"{f010dda2-9a98-4aec-af28-e4017e1be867}","it":[{"ty":"sh","nm":"","mn":"{fb537c51-1f01-4b4f-a08d-924658dbff57}","d":1,"ks":{"a":0,"k":{"c":true,"v":[[87.597,9.633],[73.066,4.356],[72.043,7.371],[87.597,9.633]],"i":[[0,0],[1.547,-1.408],[-0.660,-1.130],[-6.845,-5.750]],"o":[[-8.610,-9.342],[-1.547,1.408],[4.473,-5.226],[0,0]]}}},{"ty":"fl","nm":"","mn":"{38fa1a6a-50d9-4128-91a1-d3c4344bed57}","o":{"a":0,"k":100},"r":1,"c":{"a":0,"k":[0.059,0.047,0.024]}},{"ty":"st","nm":"","mn":"{aa5ef875-5a52-447d-9bc1-8bc3b44db02d}","o":{"a":0,"k":100},"lc":2,"lj":2,"ml":4,"w":{"a":0,"k":1.259},"c":{"a":0,"k":[0.059,0.047,0.024]}},{"ty":"tr","a":{"a":0,"k":[0,0]},"p":{"a":0,"k":[0,0]},"s":{"a":0,"k":[100,100]},"r":{"a":0,"k":0},"o":{"a":0,"k":100}}]},{"ty":"gr","nm":"mouth","mn":"{f358615b-0723-4871-989d-9d648fda40a7}","it":[{"ty":"gr","nm":"Up_lip","mn":"{c95739be-6b5b-4822-9cad-a9b996954501}","it":[{"ty":"sh","nm":"","mn":"{f6026f5a-28d1-4f49-92e2-bfddaa676c70}","d":1,"ks":{"a":0,"k":{"c":true,"v":[[50.358,42.160],[89.504,37.341],[50.358,42.160]],"i":[[0,0],[-17.395,15.139],[8.047,4.869]],"o":[[11.827,8.953],[-21.524,20.534],[0,0]]}}},{"ty":"fl","hd":true,"nm":"","mn":"{def7459a-fdde-46d3-9556-31ab81018804}","o":{"a":0,"k":0},"r":1,"c":{"a":0,"k":[0,0,0]}},{"ty":"st","nm":"","mn":"{20774c4d-0ecb-4324-be99-e576c26de504}","o":{"a":0,"k":100},"lc":2,"lj":2,"ml":4,"w":{"a":0,"k":0.873},"c":{"a":0,"k":[0.059,0.047,0.024]}},{"ty":"tr","a":{"a":0,"k":[0,0]},"p":{"a":0,"k":[0,0]},"s":{"a":0,"k":[100,100]},"r":{"a":0,"k":0},"o":{"a":0,"k":100}}]},{"ty":"gr","nm":"glossa","mn":"{98bda98e-b0e2-415b-b59d-9e9f528bd22d}","it":[{"ty":"sh","nm":"","mn":"{45628a79-4723-4398-b758-9ea3f3171146}","d":1,"ks":{"a":0,"k":{"c":true,"v":[[73.176,52.103],[60.438,54.085],[73.176,52.103]],"i":[[0,0],[1.319,-2.709],[-5.403,4.457]],"o":[[-4.506,-2.326],[2.158,2.145],[0,0]]}}},{"ty":"fl","nm":"","mn":"{11bb546a-81ba-4c30-b590-21208b5c48f6}","o":{"a":0,"k":100},"r":1,"c":{"a":0,"k":[0.914,0.498,0.706]}},{"ty":"st","nm":"","mn":"{4d78df4b-f407-453e-9522-41f2c7622732}","o":{"a":0,"k":88.235},"lc":2,"lj":2,"ml":4,"w":{"a":0,"k":0.157},"c":{"a":0,"k":[0,0,0]}},{"ty":"tr","a":{"a":0,"k":[0,0]},"p":{"a":0,"k":[0,0]},"s":{"a":0,"k":[100,100]},"r":{"a":0,"k":0},"o":{"a":0,"k":100}}]},{"ty":"gr","nm":"stoma","mn":"{adc24746-b0d3-421f-b073-47a56bcdc1a4}","it":[{"ty":"sh","nm":"","mn":"{26a3de4f-b582-486d-b17e-cf786ae2feea}","d":1,"ks":{"a":0,"k":{"c":true,"v":[[56.201,46.262],[65.500,55.505],[80.026,45.269],[56.201,46.262]],"i":[[0,0],[-2.362,-0.120],[-6.511,7.967],[8.758,5.150]],"o":[[2.229,9.143],[2.362,0.120],[-7.563,3.216],[0,0]]}}},{"ty":"fl","nm":"","mn":"{e5dbbad7-583b-490d-ae56-8965958df4d1}","o":{"a":0,"k":100},"r":1,"c":{"a":0,"k":[0.533,0.035,0.035]}},{"ty":"st","nm":"","mn":"{2de1a142-df8b-40a2-901e-ed61dc0d2296}","o":{"a":0,"k":100},"lc":2,"lj":2,"ml":4,"w":{"a":0,"k":1.273},"c":{"a":0,"k":[0,0,0]}},{"ty":"tr","a":{"a":0,"k":[0,0]},"p":{"a":0,"k":[0,0]},"s":{"a":0,"k":[100,100]},"r":{"a":0,"k":0},"o":{"a":0,"k":100}}]},{"ty":"tr","a":{"a":0,"k":[0,0]},"p":{"a":0,"k":[0,0]},"s":{"a":0,"k":[100,100]},"r":{"a":0,"k":0},"o":{"a":0,"k":100}}]},{"ty":"gr","nm":"R_eye","mn":"{a0369828-713c-42e4-942f-a5874a051105}","it":[{"ty":"gr","nm":"R_irida","mn":"{4fba4d58-b7ff-445e-a270-992565173777}","it":[{"ty":"gr","nm":"R_kori","mn":"{73d26ebb-2c37-4935-a5ea-9606ab07d1e2}","it":[{"ty":"el","nm":"","mn":"{e4cbc3be-1373-40e7-bb29-5201aea19ce5}","d":1,"p":{"a":0,"k":[337.455,321.072]},"s":{"a":0,"k":[1.032,1.017]}},{"ty":"fl","nm":"","mn":"{1b48f4a3-3abd-4ae3-9de4-6712c5ec5b30}","o":{"a":0,"k":100},"r":1,"c":{"a":0,"k":[1,0.996,0.988]}},{"ty":"st","nm":"","mn":"{42e017dc-cb17-4cba-b526-7985c65e7b04}","o":{"a":0,"k":100},"lc":2,"lj":2,"ml":4,"w":{"a":0,"k":0.277},"c":{"a":0,"k":[0.976,0.976,0.969]}},{"ty":"tr","a":{"a":0,"k":[0,0]},"p":{"a":0,"k":[0,0]},"s":{"a":0,"k":[100,100]},"r":{"a":0,"k":0},"o":{"a":0,"k":100}}]},{"ty":"gr","nm":"path33-2-1-2-4-6-8-4-2-9-5","mn":"{1d1a4c6c-09c0-41a9-9bde-197293b32c51}","it":[{"ty":"sh","nm":"","mn":"{b29d874f-19df-4b71-8558-4a0449fa4e68}","d":1,"ks":{"a":0,"k":{"c":true,"v":[[336.092,324.211],[334.814,321.248],[337.569,319.980],[338.827,322.911],[336.092,324.211]],"i":[[0,0],[-0.574,1.302],[-0.925,-0.353],[0.359,-1.150],[1.178,0.129]],"o":[[-1.178,-0.129],[0.574,-1.302],[0.925,0.353],[-0.359,1.150],[0,0]]}}},{"ty":"fl","nm":"","mn":"{89d9122e-0756-443f-af50-8b6f93a6f515}","o":{"a":0,"k":100},"r":1,"c":{"a":0,"k":[0.122,0.094,0.047]}},{"ty":"st","nm":"","mn":"{141e249f-ffd4-43f4-8e1d-0bc5960791f0}","o":{"a":0,"k":100},"lc":2,"lj":2,"ml":4,"w":{"a":0,"k":0.309},"c":{"a":0,"k":[0.188,0.176,0.059]}},{"ty":"tr","a":{"a":0,"k":[0,0]},"p":{"a":0,"k":[0,0]},"s":{"a":0,"k":[100,100]},"r":{"a":0,"k":0},"o":{"a":0,"k":100}}]},{"ty":"tr","a":{"a":0,"k":[0,0]},"p":{"a":1,"k":[{"t":0,"s":[0,0],"h":0,"o":{"x":[0.370],"y":[0]},"i":{"x":[0.411],"y":[1]},"to":[0,0],"ti":[0,0]},{"t":1.602,"s":[-0.586,0.549],"h":0,"o":{"x":[0.297],"y":[0]},"i":{"x":[0.628],"y":[0.308]},"to":[0,0],"ti":[0,0]},{"t":2,"s":[-0.556,0.521],"h":0,"o":{"x":[0.383],"y":[0.690]},"i":{"x":[0.713],"y":[1]},"to":[0,0],"ti":[0,0]},{"t":2.160,"s":[-0.538,0.557],"h":0,"o":{"x":[0.600],"y":[0]},"i":{"x":[0.400],"y":[1]},"to":[0,0],"ti":[0,0]},{"t":2.840,"s":[-0.997,-0.316],"h":0,"o":{"x":[0.287],"y":[0]},"i":{"x":[0.617],"y":[0.310]},"to":[0,0],"ti":[0,0]},{"t":3,"s":[-0.978,-0.281],"h":1,"to":[0,0],"ti":[0,0]},{"t":4,"s":[-0.488,-1.632]}]},"s":{"a":0,"k":[100,100]},"r":{"a":0,"k":0},"o":{"a":0,"k":100}}]},{"ty":"gr","nm":"R_SclerosHiton","mn":"{1e97fe51-5da4-40db-b321-28fea5e9a454}","it":[{"ty":"sh","nm":"","mn":"{bbf45273-b2ef-4b4a-8732-fd7d2809d9f2}","d":1,"ks":{"a":0,"k":{"c":true,"v":[[334.945,325.077],[339.374,325.275],[341.020,319.937],[337.094,316.597],[333.552,319.137],[334.945,325.077]],"i":[[0,0],[-1.339,-0.112],[0.462,2.259],[1.701,-0.072],[0.523,-2.061],[-1.676,-2.047]],"o":[[2.078,-0.069],[1.263,-1.177],[-0.462,-2.259],[-1.701,0.072],[-0.523,2.061],[0,0]]}}},{"ty":"fl","nm":"","mn":"{a0cc6507-bf86-4ad5-a544-eec8ef4d6df3}","o":{"a":0,"k":100},"r":1,"c":{"a":0,"k":[1,0.992,0.980]}},{"ty":"st","nm":"","mn":"{fe788ffc-3782-43f7-be93-b39dc2b7daa3}","o":{"a":0,"k":100},"lc":2,"lj":2,"ml":4,"w":{"a":0,"k":0.304},"c":{"a":0,"k":[0.188,0.176,0.059]}},{"ty":"tr","a":{"a":0,"k":[0,0]},"p":{"a":0,"k":[0,0]},"s":{"a":0,"k":[100,100]},"r":{"a":0,"k":0},"o":{"a":0,"k":100}}]},{"ty":"gr","nm":"path32-6-9-6-4-9-7-9-8-92-7-0","mn":"{5e7b8cc1-75dd-40fa-b55f-dcc33c77039e}","it":[{"ty":"sh","nm":"","mn":"{bdb84666-cd64-41cb-bb77-6e48028f919a}","d":1,"ks":{"a":0,"k":{"c":true,"v":[[73.240,22.489],[79.888,23.696],[83.389,15.950],[78.097,10.089],[72.267,13.210],[73.240,22.489]],"i":[[0,0],[-1.999,-0.444],[0.267,3.514],[2.581,0.240],[1.181,-3.014],[-2.141,-3.443]],"o":[[3.150,0.321],[2.130,-1.523],[-0.267,-3.514],[-2.581,-0.240],[-1.181,3.014],[0,0]]}}},{"ty":"fl","nm":"","mn":"{eec063b8-f417-4011-b8d3-4549f829171b}","o":{"a":0,"k":100},"r":1,"c":{"a":0,"k":[0.059,0.047,0.024]}},{"ty":"st","nm":"","mn":"{e5112b9d-0ef1-4a27-9a15-4ea81fa65bdd}","o":{"a":0,"k":100},"lc":2,"lj":2,"ml":4,"w":{"a":0,"k":0.463},"c":{"a":0,"k":[0.122,0.094,0.047]}},{"ty":"tr","a":{"a":0,"k":[0,0]},"p":{"a":0,"k":[286.033,313.275]},"s":{"a":0,"k":[65.698,65.484]},"r":{"a":0,"k":-4.507},"o":{"a":0,"k":100}}]},{"ty":"tr","a":{"a":0,"k":[0,0]},"p":{"a":0,"k":[-401.320,-511.244]},"s":{"a":0,"k":[152.326,152.594]},"r":{"a":0,"k":4.518},"o":{"a":0,"k":100}}]},{"ty":"gr","nm":"L_eye","mn":"{6b6867f4-6b10-4567-b009-e6b29e694490}","it":[{"ty":"gr","nm":"L_irida","mn":"{f7ef80a2-cc52-4afd-9a57-68e5776a39a1}","it":[{"ty":"gr","nm":"L_kori","mn":"{6369d836-1d5c-4e74-9775-0a829290ce76}","it":[{"ty":"el","nm":"","mn":"{843e7752-2e90-40e7-954a-6adc1a86b105}","d":1,"p":{"a":0,"k":[321.200,321.631]},"s":{"a":0,"k":[1.042,1.069]}},{"ty":"fl","nm":"","mn":"{2f6b587e-be76-455b-8911-38e5aeb2f966}","o":{"a":0,"k":100},"r":1,"c":{"a":0,"k":[1,0.996,0.988]}},{"ty":"st","nm":"","mn":"{3ca3cf0b-f9c3-477c-a7fc-c2759cd1f1ef}","o":{"a":0,"k":100},"lc":2,"lj":2,"ml":4,"w":{"a":0,"k":0.285},"c":{"a":0,"k":[0.984,0.984,0.984]}},{"ty":"tr","a":{"a":0,"k":[0,0]},"p":{"a":0,"k":[-0,0]},"s":{"a":0,"k":[100,100]},"r":{"a":0,"k":0},"o":{"a":0,"k":100}}]},{"ty":"gr","nm":"path33-6-6-9-6-6-2-8-3-5","mn":"{4b260c90-55fb-436d-8b39-47353a4afba0}","it":[{"ty":"sh","nm":"","mn":"{1f0cd926-67eb-4009-ad0b-5be08125688e}","d":1,"ks":{"a":0,"k":{"c":true,"v":[[319.861,324.566],[318.595,321.661],[321.324,320.418],[322.569,323.291],[319.861,324.566]],"i":[[0,0],[-0.569,1.276],[-0.916,-0.346],[0.355,-1.127],[1.166,0.126]],"o":[[-1.166,-0.126],[0.569,-1.276],[0.916,0.346],[-0.355,1.127],[0,0]]}}},{"ty":"fl","nm":"","mn":"{be2be510-fe79-41a7-974b-e72a18ee35e0}","o":{"a":0,"k":100},"r":1,"c":{"a":0,"k":[0.027,0.024,0.012]}},{"ty":"st","nm":"","mn":"{3132b77d-44f4-4570-a55e-39a86d28d6c1}","o":{"a":0,"k":100},"lc":2,"lj":2,"ml":4,"w":{"a":0,"k":0.304},"c":{"a":0,"k":[0.051,0.047,0.035]}},{"ty":"tr","a":{"a":0,"k":[0,0]},"p":{"a":0,"k":[0,0]},"s":{"a":0,"k":[100,100]},"r":{"a":0,"k":0},"o":{"a":0,"k":100}}]},{"ty":"tr","a":{"a":0,"k":[0,0]},"p":{"a":1,"k":[{"t":0,"s":[0,0],"h":0,"o":{"x":[0.370],"y":[0]},"i":{"x":[0.411],"y":[1]},"to":[0,0],"ti":[0,0]},{"t":1.602,"s":[-0.997,1.031],"h":0,"o":{"x":[0.297],"y":[0]},"i":{"x":[0.628],"y":[0.308]},"to":[0,0],"ti":[0,0]},{"t":2,"s":[-0.947,0.979],"h":0,"o":{"x":[0.383],"y":[0.690]},"i":{"x":[0.713],"y":[1]},"to":[0,0],"ti":[0,0]},{"t":2.160,"s":[-0.912,1.013],"h":0,"o":{"x":[0.600],"y":[0]},"i":{"x":[0.400],"y":[1]},"to":[0,0],"ti":[0,0]},{"t":2.840,"s":[-1.757,0.181],"h":0,"o":{"x":[0.287],"y":[0]},"i":{"x":[0.617],"y":[0.310]},"to":[0,0],"ti":[0,0]},{"t":3,"s":[-1.722,0.215],"h":1,"to":[0,0],"ti":[0,0]},{"t":4,"s":[-0.641,-0.886]}]},"s":{"a":0,"k":[100,100]},"r":{"a":0,"k":0},"o":{"a":0,"k":100}}]},{"ty":"gr","nm":"g2-3-0-0-5-89-4-01-4-1","mn":"{8dc1f7cd-407d-4089-b728-16628a51bdc0}","it":[{"ty":"gr","nm":"L_SclirosHiton","mn":"{5c8484a3-f0ce-452d-a1be-f42024f114db}","it":[{"ty":"sh","nm":"","mn":"{fcced2b7-34d1-4302-a683-5e09f94c3346}","d":1,"ks":{"a":0,"k":{"c":true,"v":[[253.373,275.188],[258.210,274.608],[259.706,269.572],[255.617,266.280],[251.800,269.247],[253.373,275.188]],"i":[[0,0],[-1.490,-0.034],[0.462,2.259],[1.729,-0.026],[0.523,-2.061],[-1.989,-1.911]],"o":[[1.899,-0.490],[1.263,-1.177],[-0.462,-2.259],[-1.729,0.026],[-0.523,2.061],[0,0]]}}},{"ty":"fl","nm":"","mn":"{8f293503-40c5-46c1-aa4d-e18500a05bde}","o":{"a":0,"k":100},"r":1,"c":{"a":0,"k":[1,0.992,0.980]}},{"ty":"st","nm":"","mn":"{bb52d5d0-88d3-424e-a278-b1e0c7933f7a}","o":{"a":0,"k":100},"lc":2,"lj":2,"ml":4,"w":{"a":0,"k":0.304},"c":{"a":0,"k":[0.051,0.047,0.035]}},{"ty":"tr","a":{"a":0,"k":[0,0]},"p":{"a":0,"k":[0,0]},"s":{"a":0,"k":[100,100]},"r":{"a":0,"k":0},"o":{"a":0,"k":100}}]},{"ty":"gr","nm":"path32-5-3-4-49-3-5-0-3-9-8","mn":"{b3ca5bf8-9095-467b-b951-1659b4f30f40}","it":[{"ty":"sh","nm":"","mn":"{4fc68af6-3756-4741-849b-02ce7dd0a162}","d":1,"ks":{"a":0,"k":{"c":true,"v":[[253.373,275.188],[258.210,274.608],[259.706,269.572],[255.617,266.280],[251.800,269.247],[253.373,275.188]],"i":[[0,0],[-1.490,-0.034],[0.462,2.259],[1.729,-0.026],[0.523,-2.061],[-1.989,-1.911]],"o":[[1.899,-0.490],[1.263,-1.177],[-0.462,-2.259],[-1.729,0.026],[-0.523,2.061],[0,0]]}}},{"ty":"fl","nm":"","mn":"{a8b70332-7d38-4d63-9864-bb1347a717ee}","o":{"a":0,"k":100},"r":1,"c":{"a":0,"k":[0.071,0.055,0.027]}},{"ty":"gs","nm":"linearGradient1","mn":"{c11c9455-e1c3-412b-b4fc-185f0db81290}","o":{"a":0,"k":100},"lc":2,"lj":2,"ml":4,"w":{"a":0,"k":0.304},"s":{"a":0,"k":[251.385,270.734]},"e":{"a":0,"k":[260,270.734]},"t":1,"h":{"a":0,"k":0},"a":{"a":0,"k":0},"g":{"p":2,"k":{"a":0,"k":[0,0.027,0.024,0.012,0,0.059,0.047,0.024,0,1,0,1]}}},{"ty":"tr","a":{"a":0,"k":[0,0]},"p":{"a":0,"k":[14.967,-12.600]},"s":{"a":0,"k":[99.933,100.067]},"r":{"a":0,"k":2.701},"o":{"a":0,"k":100}}]},{"ty":"tr","a":{"a":0,"k":[0,0]},"p":{"a":0,"k":[65.057,50.882]},"s":{"a":0,"k":[100,100]},"r":{"a":0,"k":0},"o":{"a":0,"k":100}}]},{"ty":"tr","a":{"a":0,"k":[0,0]},"p":{"a":0,"k":[-395.576,-440.432]},"s":{"a":0,"k":[137.380,145.526]},"r":{"a":0,"k":-1.203},"o":{"a":0,"k":100}}]},{"ty":"gr","nm":"path25-2-0-3-1-7-2-5","mn":"{81082814-b58c-4e92-bfb6-8d215baeb71b}","it":[{"ty":"sh","nm":"","mn":"{3c178269-7e67-4f67-a630-0d6ec34eb30a}","d":1,"ks":{"a":0,"k":{"c":true,"v":[[93.429,49.771],[97.897,29.314],[82.189,10.861],[62.389,11.953],[51.679,27.203],[49.499,43.433],[66.699,59.047],[93.429,49.771]],"i":[[0,0],[1.758,7.816],[6.470,1.705],[5.787,-3.149],[2.037,-5.660],[-1.895,-7.419],[-11.966,-0.261],[-6.643,5.887]],"o":[[6.643,-5.887],[-1.758,-7.816],[-6.470,-1.705],[-5.787,3.149],[-1.157,0.475],[1.895,7.419],[11.966,0.261],[0,0]]}}},{"ty":"fl","hd":true,"nm":"","mn":"{6c9e48e4-f1e6-45b0-b4df-d977ae48ed85}","o":{"a":0,"k":0},"r":1,"c":{"a":0,"k":[0,0,0]}},{"ty":"st","nm":"","mn":"{ea5d961e-b743-48d2-a760-f197a95344f0}","o":{"a":0,"k":100},"lc":2,"lj":2,"ml":4,"w":{"a":0,"k":0.672},"c":{"a":0,"k":[0,0,0]}},{"ty":"tr","a":{"a":0,"k":[0,0]},"p":{"a":0,"k":[0,0]},"s":{"a":0,"k":[100,100]},"r":{"a":0,"k":0},"o":{"a":0,"k":100}}]},{"ty":"gr","nm":"path17-5-6-9-2-5-4-0-3","mn":"{9b047e21-649d-484d-82be-70cd6104cd89}","it":[{"ty":"sh","nm":"","mn":"{9f7d5adc-e21b-4916-b26d-10704cecb053}","d":1,"ks":{"a":0,"k":{"c":true,"v":[[98.231,30.942],[51.452,27.499],[53.276,52.110],[71.241,58.852],[91.134,51.399],[98.231,30.942]],"i":[[0,0],[8.805,-3.740],[-5.586,-8.095],[-2.819,0.163],[-8.019,5.952],[1.390,9.627]],"o":[[-20.080,-8.247],[-3.315,5.655],[5.586,8.095],[2.819,-0.163],[8.019,-5.952],[0,0]]}}},{"ty":"fl","nm":"","mn":"{6aabb804-a71f-4577-92fa-27dfb727ea30}","o":{"a":0,"k":100},"r":1,"c":{"a":0,"k":[0.533,0.533,0.537]}},{"ty":"st","nm":"","mn":"{2c882db4-1ded-4e8a-808b-1232b5353955}","o":{"a":0,"k":100},"lc":2,"lj":2,"ml":4,"w":{"a":0,"k":0.527},"c":{"a":0,"k":[0.188,0.176,0.059]}},{"ty":"tr","a":{"a":0,"k":[0,0]},"p":{"a":0,"k":[0,0]},"s":{"a":0,"k":[100,100]},"r":{"a":0,"k":0},"o":{"a":0,"k":100}}]},{"ty":"gr","nm":"path1-4-9-7-0-0-2-1-6","mn":"{126cc2ff-c716-4b12-8962-f3639fe8b5e9}","it":[{"ty":"sh","nm":"","mn":"{4b676b8f-027d-41e7-b053-56702266e2d3}","d":1,"ks":{"a":0,"k":{"c":true,"v":[[51.005,30.303],[59.753,13.701],[86.933,13.577],[98.442,31.369],[51.005,30.303]],"i":[[0,0],[-5.417,4.917],[-6.446,-5.110],[-2.759,-8.126],[8.993,-0.509]],"o":[[0.728,-3.507],[5.417,-4.917],[6.446,5.110],[-13.104,0.829],[0,0]]}}},{"ty":"fl","nm":"","mn":"{e8593d76-b9d1-4e4b-bbb0-6e020293c609}","o":{"a":0,"k":100},"r":1,"c":{"a":0,"k":[0.533,0.533,0.537]}},{"ty":"st","nm":"","mn":"{f8cd2d22-f0b1-4629-be16-2c7518dea8a2}","o":{"a":0,"k":100},"lc":2,"lj":2,"ml":4,"w":{"a":0,"k":0.506},"c":{"a":0,"k":[0.188,0.176,0.059]}},{"ty":"tr","a":{"a":0,"k":[0,0]},"p":{"a":0,"k":[0,0]},"s":{"a":0,"k":[100,100]},"r":{"a":0,"k":0},"o":{"a":0,"k":100}}]},{"ty":"gr","nm":"white_front","mn":"{b8316224-abd3-40ae-837e-9dc432741094}","it":[{"ty":"sh","nm":"","mn":"{8e77f22a-4f2b-4e96-8258-f3b5102a6c04}","d":1,"ks":{"a":0,"k":{"c":true,"v":[[97.504,104.690],[97.499,95.680],[96.994,87.122],[94.594,78.009],[88.325,71.753],[90.286,66.374],[86.548,59.832],[84.416,54.162],[78.569,55.573],[81.111,61.640],[84.653,67.721],[89.346,80.054],[92.641,95.256],[91.708,108.155],[90.934,114.098],[94.922,122.680],[96.844,112.793],[97.504,104.690]],"i":[[0,0],[-0.958,6.232],[0.264,3.510],[1.141,2.203],[0.655,2.197],[1.030,2.324],[-0.339,3.110],[1.808,2.506],[0.375,-3.447],[-0.946,-2.102],[-3.109,-2.245],[-6.561,-2.504],[0.463,-7.404],[0.073,-6.674],[0.630,-1.953],[-0.993,-2.261],[-0.682,4.825],[0.119,0.937]],"o":[[-0.378,-2.317],[0.223,-3.094],[-0.264,-3.510],[-1.141,-2.203],[-0.420,-1.408],[-0.399,-0.901],[0.263,-2.414],[-1.669,-1.917],[1.047,3.403],[0.480,1.719],[-1.493,4.240],[2.438,0.407],[-0.463,7.404],[0.410,2.073],[1.145,2.355],[1.614,0.041],[0.682,-4.825],[0,0]]}}},{"ty":"fl","nm":"","mn":"{16652a8e-1716-4702-8951-574ab29c3d1d}","o":{"a":0,"k":100},"r":1,"c":{"a":0,"k":[0.984,0.976,0.976]}},{"ty":"st","nm":"","mn":"{a4042565-94ee-4ef0-bb33-175d52cab734}","o":{"a":0,"k":100},"lc":2,"lj":2,"ml":4,"w":{"a":0,"k":1.100},"c":{"a":0,"k":[0.031,0.027,0.012]}},{"ty":"tr","a":{"a":0,"k":[0,0]},"p":{"a":0,"k":[0,0]},"s":{"a":0,"k":[100,100]},"r":{"a":0,"k":0},"o":{"a":0,"k":100}}]},{"ty":"gr","nm":"L_hand","mn":"{c71399d4-9bdd-4a49-9621-dde7d8afd7d6}","it":[{"ty":"sh","nm":"","mn":"{54262738-3233-4757-8306-035c2f87d0b4}","d":1,"ks":{"a":0,"k":{"c":true,"v":[[87.743,80.198],[66.579,107.632],[62.136,104.229],[54.995,104.923],[55.054,100.368],[48.885,99.845],[52.012,95.457],[45.808,92.353],[85.749,71.105],[90.416,76.898]],"i":[[0,0],[11.458,-16.937],[-3.263,2.410],[3.167,1.860],[-2.921,1.974],[2.519,2.101],[-3.237,0.882],[-0.385,1.908],[-4.882,6.748],[-2.376,-1.513]],"o":[[-7.320,11.265],[-8.821,-0.423],[-2.941,1.552],[-2.614,-1.885],[-4.489,1.239],[-2.158,-1.801],[-7.868,3.169],[16.467,-4.614],[1.412,3.050],[0,0]]}}},{"ty":"fl","nm":"","mn":"{40876b58-6d4a-4e95-80f9-7c3de578b95f}","o":{"a":0,"k":100},"r":1,"c":{"a":0,"k":[0.533,0.533,0.537]}},{"ty":"st","nm":"","mn":"{5f59d0ca-5b7c-4cd6-b4f6-a55a1413df3f}","o":{"a":0,"k":100},"lc":1,"lj":1,"ml":4,"w":{"a":0,"k":1.500},"c":{"a":0,"k":[0.027,0.024,0.012]}},{"ty":"tr","a":{"a":0,"k":[41.716,96.109]},"p":{"a":0,"k":[41.716,96.109]},"s":{"a":0,"k":[100,100]},"r":{"a":0,"k":0},"o":{"a":0,"k":100}}]},{"ty":"gr","nm":"stomaxi","mn":"{fc1722f0-d04a-4551-9dfc-09560d32edca}","it":[{"ty":"sh","nm":"","mn":"{2263c55f-0b0c-414c-87ca-482338ef27d7}","d":1,"ks":{"a":0,"k":{"c":true,"v":[[80.019,61.174],[83.991,67.961],[89.590,80.637],[91.922,95.190],[91.085,109.909],[89.649,115.237],[69.025,118.764],[60.706,100.618],[64.628,62.468],[80.019,61.174]],"i":[[0,0],[-2.729,-1.642],[-3.345,-0.928],[-0.022,-6.386],[-0.432,-2],[0.658,-2.609],[2.667,1.368],[2.359,12.376],[-3.341,5.284],[-4.256,2.835]],"o":[[1.178,2.541],[-2.506,6.443],[2.638,5.047],[-0.580,4.968],[-0.680,4.291],[-5.988,4.862],[-3.924,-2.013],[-3.064,-16.078],[5.001,4.104],[0,0]]}}},{"ty":"sh","nm":"","mn":"{3550600b-6b85-4ee5-b479-d0feeece4fa0}","d":1,"ks":{"a":0,"k":{"c":false,"v":[[80.819,69.840],[61.829,70.472]],"i":[[0,0],[1.774,5.034]],"o":[[-6.048,5.975],[0,0]]}}},{"ty":"sh","nm":"","mn":"{a9421982-3f9a-4688-be42-f2c8704b51fb}","d":1,"ks":{"a":0,"k":{"c":false,"v":[[83.081,81.194],[60.677,84.133]],"i":[[0,0],[3.079,6.691]],"o":[[-6.502,8.164],[0,0]]}}},{"ty":"sh","nm":"","mn":"{be906948-e570-4d73-872f-3109308d6a62}","d":1,"ks":{"a":0,"k":{"c":false,"v":[[87.885,92.803],[61.440,96.841]],"i":[[0,0],[3.749,5.747]],"o":[[-9.907,9.814],[0,0]]}}},{"ty":"sh","nm":"","mn":"{29d23bec-a49f-4eea-b4f5-6c21bff7a900}","d":1,"ks":{"a":0,"k":{"c":false,"v":[[88.912,104.632],[63.817,108.308]],"i":[[0,0],[6.477,5.515]],"o":[[-7.811,6.226],[0,0]]}}},{"ty":"st","nm":"","mn":"{e5cbf64d-f47d-4f1b-8490-ca11dafdf8ec}","o":{"a":0,"k":100},"lc":2,"lj":2,"ml":4,"w":{"a":0,"k":0.470},"c":{"a":0,"k":[0.286,0.129,0.035]}},{"ty":"fl","nm":"","mn":"{04f767ff-c122-4e30-9e9c-dc6789668b58}","o":{"a":0,"k":100},"r":1,"c":{"a":0,"k":[0.882,0.847,0.616]}},{"ty":"tr","a":{"a":0,"k":[0,0]},"p":{"a":0,"k":[0,0]},"s":{"a":0,"k":[100,100]},"r":{"a":0,"k":0},"o":{"a":0,"k":100}}]},{"ty":"gr","nm":"L_leg","mn":"{6025caf7-0bf2-400d-8d54-43a073a4d443}","it":[{"ty":"sh","nm":"","mn":"{28597092-c7fa-4c1a-a622-886e81f79413}","d":1,"ks":{"a":0,"k":{"c":true,"v":[[90.144,113.893],[99.322,134.592],[94.282,135.806],[91.214,140.971],[87.525,138.557],[83.957,142.433],[81.966,138.043],[76.273,140.598],[79.674,124.775],[79.503,113.667],[90.144,113.893]],"i":[[0,0],[-3.462,-9.892],[0.307,3.451],[3.130,-1.161],[0.125,2.994],[2.998,-0.599],[-0.928,2.636],[1.362,1.253],[-0.825,7.036],[0.116,6.789],[-1.208,-2.777]],"o":[[2.478,6.162],[-4.835,5.712],[-0.229,2.787],[-2.870,0.776],[-1.273,3.665],[-2.569,0.513],[-1.417,6.944],[2.428,-7.094],[0.354,-6.234],[6.920,-2.923],[0,0]]}}},{"ty":"fl","nm":"","mn":"{6b28967c-2865-4f47-9a28-d3548d4b5f93}","o":{"a":0,"k":100},"r":1,"c":{"a":0,"k":[0.533,0.533,0.537]}},{"ty":"st","nm":"","mn":"{ca674f63-a638-418a-87da-aad81446226f}","o":{"a":0,"k":100},"lc":2,"lj":2,"ml":4,"w":{"a":0,"k":1.484},"c":{"a":0,"k":[0.027,0.024,0.012]}},{"ty":"tr","a":{"a":0,"k":[88.611,126.641]},"p":{"a":0,"k":[88.611,126.641]},"s":{"a":0,"k":[100,100]},"r":{"a":0,"k":0},"o":{"a":0,"k":100}}]},{"ty":"gr","nm":"neck","mn":"{014cfa51-3577-44d1-8ada-2720121c3963}","it":[{"ty":"sh","nm":"","mn":"{2f331141-ec3e-4674-9681-c1ca977b4980}","d":1,"ks":{"a":0,"k":{"c":true,"v":[[65.188,64.265],[65.249,44.559],[79.595,43.834],[77.240,68.054],[65.188,64.265]],"i":[[0,0],[-0.567,14.451],[-5.406,0.809],[3.632,-3.610],[3.190,3.281]],"o":[[0.279,-3],[5.645,-3.284],[-1.112,16.934],[-3.116,3.104],[0,0]]}}},{"ty":"fl","nm":"","mn":"{a604c795-df80-4fba-b3da-6f3b9c247ea2}","o":{"a":0,"k":100},"r":1,"c":{"a":0,"k":[0.533,0.533,0.537]}},{"ty":"st","nm":"","mn":"{1f4a3442-18d7-4894-be7a-cfc6ebf18b00}","o":{"a":0,"k":100},"lc":2,"lj":2,"ml":4,"w":{"a":0,"k":1.395},"c":{"a":0,"k":[0.137,0.141,0.133]}},{"ty":"tr","a":{"a":0,"k":[71.152,57.343]},"p":{"a":0,"k":[71.152,57.343]},"s":{"a":0,"k":[100,100]},"r":{"a":0,"k":0},"o":{"a":0,"k":100}}]},{"ty":"gr","nm":"R_hand","mn":"{54430fa1-b557-41c9-951a-111b04b4cc3d}","it":[{"ty":"sh","nm":"","mn":"{66f12dae-0ad0-4b05-879e-2bba10050b50}","d":1,"ks":{"a":0,"k":{"c":true,"v":[[70.582,87.254],[27.826,73.919],[29.295,67.511],[25.584,60.165],[30.098,58.044],[27.998,51.160],[33.648,52.419],[34.076,44.259],[48.702,60.262],[66.387,73.128],[78.043,78.584],[70.582,87.254]],"i":[[0,0],[21.548,4.200],[-3.758,-2.354],[-0.490,4.297],[-3.184,-2.194],[-1.003,3.716],[-2.241,-3.058],[-2.043,0.500],[-6.876,-6.371],[-6.044,-3.357],[-1.690,0.241],[3.800,-2.007]],"o":[[-14.204,-2.470],[-3.323,-9.688],[-2.777,-2.418],[0.749,-3.715],[-3.124,-4.233],[0.860,-3.184],[-6.459,-6.941],[6.066,8.154],[13.901,11.692],[5.091,7.361],[0.092,4.315],[0,0]]}}},{"ty":"fl","nm":"","mn":"{d19a50b0-7489-4c1d-829f-246dc26a9782}","o":{"a":0,"k":100},"r":1,"c":{"a":0,"k":[0.533,0.533,0.537]}},{"ty":"st","nm":"","mn":"{499c4092-fc79-4a04-aa63-a160312c63e0}","o":{"a":0,"k":100},"lc":2,"lj":1,"ml":4,"w":{"a":0,"k":1.443},"c":{"a":0,"k":[0.027,0.024,0.012]}},{"ty":"tr","a":{"a":0,"k":[0,0]},"p":{"a":0,"k":[0,0]},"s":{"a":0,"k":[100,100]},"r":{"a":0,"k":0},"o":{"a":0,"k":100}}]},{"ty":"gr","nm":"R_Leg","mn":"{e2912f2a-c3d0-4c8f-bba5-e88e4fea286b}","it":[{"ty":"sh","nm":"","mn":"{eca0af44-2fa2-4dd1-a627-4b9e0aa52d9b}","d":1,"ks":{"a":0,"k":{"c":true,"v":[[69.531,106.769],[45.065,128.101],[51.450,129.208],[52.725,133.249],[57.585,130.957],[59.472,134.324],[62.963,130.487],[66.531,132.647],[75.272,114.169]],"i":[[0,0],[7.100,-10.061],[-2.185,1.889],[-2.924,-0.904],[-2.283,1.746],[-2.787,-0.439],[-1.778,2.617],[-1.227,1.069],[-4.110,5.220]],"o":[[-5.973,3.362],[4.616,4.657],[-2.178,2.056],[2.674,0.589],[-2.576,2.769],[2.389,0.377],[-1.621,4.192],[1.389,-5.666],[0,0]]}}},{"ty":"fl","nm":"","mn":"{798da226-f61a-4e03-82fc-b197e8aced22}","o":{"a":0,"k":100},"r":1,"c":{"a":0,"k":[0.533,0.533,0.537]}},{"ty":"st","nm":"","mn":"{5fe0641f-93bc-4986-9612-4f4c73a5205e}","o":{"a":0,"k":100},"lc":2,"lj":2,"ml":4,"w":{"a":0,"k":1.401},"c":{"a":0,"k":[0.027,0.024,0.012]}},{"ty":"tr","a":{"a":0,"k":[58.210,119.791]},"p":{"a":0,"k":[58.210,119.791]},"s":{"a":0,"k":[100,100]},"r":{"a":0,"k":0},"o":{"a":0,"k":100}}]},{"ty":"gr","nm":"g336-0","mn":"{12c99e19-e7a5-44db-8cb7-f19bbc38a3af}","it":[{"ty":"gr","nm":"path24","mn":"{b1dcfa2d-dcab-4ec7-9b84-7d9624affa5a}","it":[{"ty":"sh","nm":"","mn":"{7f487857-da95-4489-b3dd-8c0ca38a9217}","d":1,"ks":{"a":0,"k":{"c":true,"v":[[5.260,169.662],[-3.323,168.575],[-7.209,150.983],[-9.006,138.324],[-7.665,125.231],[-2.803,117.626],[-2.420,107.344],[0.578,99.087],[6.533,101.654],[0.239,113.821],[-2.515,126.099],[-1.211,156.455],[5.260,169.662]],"i":[[0,0],[0.334,2.166],[-0.400,4.887],[0.572,8.676],[-1.498,2.250],[2.035,2.150],[-0.541,6.446],[-3.382,2.585],[-0.930,-2.193],[4.465,-4.973],[4.508,-2.834],[0.029,-4.429],[-1.577,-4.682]],"o":[[-2.880,1.772],[-1.181,-7.652],[0.122,-4.964],[-0.281,-4.267],[0.689,-1.943],[-5.276,-5.573],[0.191,-2.271],[3.749,-0.669],[-4.580,1.396],[2.272,2.610],[-5.906,5.105],[1.778,5.193],[0,0]]}}},{"ty":"fl","nm":"","mn":"{027b99c9-0490-4dfd-b012-fb2c2b7f0569}","o":{"a":0,"k":100},"r":1,"c":{"a":0,"k":[0.996,0.996,0.996]}},{"ty":"st","nm":"","mn":"{41d0607f-7380-4d23-b10f-73f9da381eca}","o":{"a":0,"k":100},"lc":2,"lj":2,"ml":4,"w":{"a":0,"k":1.816},"c":{"a":0,"k":[0.027,0.024,0.012]}},{"ty":"tr","a":{"a":0,"k":[0,0]},"p":{"a":0,"k":[0,0]},"s":{"a":0,"k":[100,100]},"r":{"a":0,"k":0},"o":{"a":0,"k":100}}]},{"ty":"gr","nm":"cavuki","mn":"{17502b1c-1d11-4277-945d-68951d2708b1}","it":[{"ty":"gr","nm":"perigramma","mn":"{3fcf23d3-c2d8-43ca-8c38-30721febbe99}","it":[{"ty":"sh","nm":"","mn":"{77fc776a-6320-42e6-a98d-9e4920d82f78}","d":1,"ks":{"a":0,"k":{"c":false,"v":[[-1.212,168.941],[-33.407,127.116],[1.619,99.259]],"i":[[0,0],[-0.142,21.028],[-20.063,-9.426]],"o":[[-9.093,-13.445],[0.142,-21.028],[0,0]]}}},{"ty":"fl","hd":true,"nm":"","mn":"{835924fa-993b-4964-ab0b-7104418f6b88}","o":{"a":0,"k":0},"r":1,"c":{"a":0,"k":[0,0,0]}},{"ty":"st","nm":"","mn":"{c5b28558-18c3-4902-b2eb-23af2a0cbc96}","o":{"a":0,"k":100},"lc":2,"lj":2,"ml":4,"w":{"a":0,"k":1.140},"c":{"a":0,"k":[0.059,0.047,0.024]}},{"ty":"tr","a":{"a":0,"k":[0,0]},"p":{"a":0,"k":[0,0]},"s":{"a":0,"k":[100,100]},"r":{"a":0,"k":0},"o":{"a":0,"k":100}}]},{"ty":"gr","nm":"path20","mn":"{7ee6aa50-7beb-403d-a730-5b1895f7f655}","it":[{"ty":"sh","nm":"","mn":"{8a1f6d65-3d79-496b-a13f-e8ae92f6f567}","d":1,"ks":{"a":0,"k":{"c":true,"v":[[-4.279,120.592],[-9.012,120.549],[-6.022,114.255],[-3.511,116.645],[-4.279,120.592]],"i":[[0,0],[1.904,-0.092],[-0.555,1.488],[-0.695,-0.323],[1.602,-1.282]],"o":[[-1.624,-0.402],[-0.316,-1.249],[2.121,-0.177],[1.006,0.468],[0,0]]}}},{"ty":"fl","nm":"","mn":"{77ed6dc1-d94b-4ebf-b360-267250733718}","o":{"a":0,"k":100},"r":1,"c":{"a":0,"k":[1,0.929,0]}},{"ty":"st","nm":"","mn":"{eb07e6ed-b47e-4f39-aa51-46a319e07085}","o":{"a":0,"k":100},"lc":2,"lj":2,"ml":4,"w":{"a":0,"k":1.400},"c":{"a":0,"k":[0.059,0.047,0.024]}},{"ty":"tr","a":{"a":0,"k":[0,0]},"p":{"a":0,"k":[0,0]},"s":{"a":0,"k":[100,100]},"r":{"a":0,"k":0},"o":{"a":0,"k":100}}]},{"ty":"gr","nm":"path18","mn":"{40fee65f-2e10-41d2-b216-5531e18213fd}","it":[{"ty":"sh","nm":"","mn":"{8e3be7ba-933d-4e2e-a053-8e960fc8c7b0}","d":1,"ks":{"a":0,"k":{"c":true,"v":[[-16.535,107.895],[-10.575,96.970],[-0.081,98.851],[-2.915,106.099],[-5.526,111.996],[-16.535,107.895]],"i":[[0,0],[-2.505,3.493],[0.120,-0.173],[0.155,-4.020],[2.036,-2.491],[0.867,0.371]],"o":[[1.747,-4.184],[4.074,0.018],[-3.912,5.635],[-0.059,1.522],[-4.322,-2.591],[0,0]]}}},{"ty":"fl","nm":"","mn":"{78ad1e08-1377-49ed-8c22-badc97a81bf7}","o":{"a":0,"k":100},"r":1,"c":{"a":0,"k":[1,0.929,0]}},{"ty":"st","nm":"","mn":"{a46e89bc-42eb-4516-94af-6a0697c3078f}","o":{"a":0,"k":100},"lc":2,"lj":2,"ml":4,"w":{"a":0,"k":1.500},"c":{"a":0,"k":[0.059,0.047,0.024]}},{"ty":"tr","a":{"a":0,"k":[0,0]},"p":{"a":0,"k":[0,0]},"s":{"a":0,"k":[100,100]},"r":{"a":0,"k":0},"o":{"a":0,"k":100}}]},{"ty":"gr","nm":"path23","mn":"{5d258eb9-1297-4604-88cf-c5ab5562ad5d}","it":[{"ty":"sh","nm":"","mn":"{d4054936-91e9-4d67-bfdf-675bc1cbbcd8}","d":1,"ks":{"a":0,"k":{"c":true,"v":[[-4.175,164.051],[-17.014,152.553],[-18.609,139.012],[-8.611,144.634],[-4.175,164.051]],"i":[[0,0],[5.067,4.386],[0.178,4.599],[-4.578,-1.931],[-3.253,-8.209]],"o":[[-2.380,-3.015],[-0.568,-3.222],[2.645,2.173],[-0.201,0.043],[0,0]]}}},{"ty":"fl","nm":"","mn":"{ad27d88f-6b1d-42bb-8108-e10d0b5033c3}","o":{"a":0,"k":100},"r":1,"c":{"a":0,"k":[1,0.929,0]}},{"ty":"st","nm":"","mn":"{5f2a6ef5-82ab-4fcf-ae5b-ee7b06fc132e}","o":{"a":0,"k":100},"lc":2,"lj":2,"ml":4,"w":{"a":0,"k":1.500},"c":{"a":0,"k":[0.059,0.047,0.024]}},{"ty":"tr","a":{"a":0,"k":[0,0]},"p":{"a":0,"k":[0,0]},"s":{"a":0,"k":[100,100]},"r":{"a":0,"k":0},"o":{"a":0,"k":100}}]},{"ty":"gr","nm":"path3","mn":"{bf8333d7-485f-41a3-93c8-416e73d5ff42}","it":[{"ty":"sh","nm":"","mn":"{ec10a915-ab90-43f9-8ad7-306bdfeb0573}","d":1,"ks":{"a":0,"k":{"c":true,"v":[[-19.472,150.949],[-27.389,143.389],[-28.562,132.616],[-21.072,137.367],[-19.472,150.949]],"i":[[0,0],[0.943,1.380],[-0.040,2.136],[-2.886,-1.449],[-0.934,-5.241]],"o":[[-4.899,-3.726],[-1.058,-4.490],[2.186,1.905],[-0.249,4.462],[0,0]]}}},{"ty":"fl","nm":"","mn":"{d306a54b-9ad2-4edc-a8e9-ec70eb00236e}","o":{"a":0,"k":100},"r":1,"c":{"a":0,"k":[1,0.929,0]}},{"ty":"st","nm":"","mn":"{1110e9a8-d1d2-4a2f-bce2-4ac1f4eba776}","o":{"a":0,"k":100},"lc":2,"lj":2,"ml":4,"w":{"a":0,"k":1.300},"c":{"a":0,"k":[0.059,0.047,0.024]}},{"ty":"tr","a":{"a":0,"k":[0,0]},"p":{"a":0,"k":[0,0]},"s":{"a":0,"k":[100,100]},"r":{"a":0,"k":0},"o":{"a":0,"k":100}}]},{"ty":"gr","nm":"path17","mn":"{7f938797-59e9-4d24-b58c-bd478fd39967}","it":[{"ty":"sh","nm":"","mn":"{07ea2491-4a64-4254-9c58-cfb5c5a53760}","d":1,"ks":{"a":0,"k":{"c":true,"v":[[-23.708,106.749],[-20.542,100.012],[-12.936,97.218],[-18.324,107.478],[-23.708,106.749]],"i":[[0,0],[-1.875,3.167],[-2.378,0.451],[1.211,-3.734],[1.761,-0.124]],"o":[[0.878,-3.008],[2.643,-1.705],[-2.017,2.002],[-1.937,-0.971],[0,0]]}}},{"ty":"fl","nm":"","mn":"{fa64f6b7-d51c-4ec6-ae3d-9bb344346fc6}","o":{"a":0,"k":100},"r":1,"c":{"a":0,"k":[1,0.929,0]}},{"ty":"st","nm":"","mn":"{acc1d8f9-4b48-437e-9e4d-ccbfe21f513f}","o":{"a":0,"k":100},"lc":2,"lj":2,"ml":4,"w":{"a":0,"k":1.300},"c":{"a":0,"k":[0.059,0.047,0.024]}},{"ty":"tr","a":{"a":0,"k":[0,0]},"p":{"a":0,"k":[0,0]},"s":{"a":0,"k":[100,100]},"r":{"a":0,"k":0},"o":{"a":0,"k":100}}]},{"ty":"gr","nm":"path22","mn":"{199cd883-f55a-4263-a490-7dcb071702e7}","it":[{"ty":"sh","nm":"","mn":"{a7c8baba-3406-4798-b7c7-49e137229372}","d":1,"ks":{"a":0,"k":{"c":true,"v":[[-8.867,142.085],[-18.765,136.296],[-19.222,124.725],[-9.068,128.038],[-8.867,142.085]],"i":[[0,0],[3.280,2.197],[-0.503,2.177],[-2.248,-0.432],[-0.781,-6.980]],"o":[[-3.832,-1.277],[0,0],[3.245,1.312],[0.102,1.980],[0,0]]}}},{"ty":"fl","nm":"","mn":"{36e7f2f3-2d6f-448e-8e68-d190d6e98ae3}","o":{"a":0,"k":100},"r":1,"c":{"a":0,"k":[1,0.929,0]}},{"ty":"st","nm":"","mn":"{c91d8a19-8834-46c7-a6a3-9f49627c11e5}","o":{"a":0,"k":100},"lc":2,"lj":2,"ml":4,"w":{"a":0,"k":1.500},"c":{"a":0,"k":[0.059,0.047,0.024]}},{"ty":"tr","a":{"a":0,"k":[0,0]},"p":{"a":0,"k":[0,0]},"s":{"a":0,"k":[100,100]},"r":{"a":0,"k":0},"o":{"a":0,"k":100}}]},{"ty":"gr","nm":"path21","mn":"{78e2d606-d7a3-4066-aac7-166507246413}","it":[{"ty":"sh","nm":"","mn":"{e3e0f41a-50e0-4bf3-8f1e-c556645a61d5}","d":1,"ks":{"a":0,"k":{"c":true,"v":[[-14.247,124.390],[-10.343,123.001],[-6.286,122.316],[-7.833,126.065],[-13.553,124.649]],"i":[[0,0],[-0.114,1.632],[-2.197,-0.293],[-0.618,-1.107],[0,0]],"o":[[2.744,0.005],[0.048,-0.691],[-1.729,1.755],[-2.602,-0.737],[0,0]]}}},{"ty":"fl","nm":"","mn":"{f1a2f274-80f4-4631-bc61-40223719d657}","o":{"a":0,"k":100},"r":1,"c":{"a":0,"k":[1,0.929,0]}},{"ty":"st","nm":"","mn":"{8fe67172-f4be-4b92-9674-2687bf4f5095}","o":{"a":0,"k":100},"lc":2,"lj":2,"ml":4,"w":{"a":0,"k":1.400},"c":{"a":0,"k":[0.059,0.047,0.024]}},{"ty":"tr","a":{"a":0,"k":[0,0]},"p":{"a":0,"k":[0,0]},"s":{"a":0,"k":[100,100]},"r":{"a":0,"k":0},"o":{"a":0,"k":100}}]},{"ty":"gr","nm":"path19","mn":"{91dcdf32-f17e-4087-9af8-ab3bf96a5636}","it":[{"ty":"sh","nm":"","mn":"{3ce2eabe-36d2-4cb5-9760-d7f682e60a86}","d":1,"ks":{"a":0,"k":{"c":true,"v":[[-12.433,122.319],[-19.380,122.477],[-17.394,109.709],[-8.106,113.055],[-10.370,117.532],[-12.433,122.319]],"i":[[0,0],[0,0],[-1.358,3.344],[-0.810,-0.748],[0.378,-1.371],[1.469,-1.093]],"o":[[-3.687,0.785],[0.034,-5.765],[3.533,1.143],[0.810,0.748],[-0.378,1.371],[0,0]]}}},{"ty":"fl","nm":"","mn":"{53676942-a6d9-4ccc-9a86-725a72704d11}","o":{"a":0,"k":100},"r":1,"c":{"a":0,"k":[1,0.929,0]}},{"ty":"st","nm":"","mn":"{a4572535-1bf4-461a-a6d7-35603ca25d46}","o":{"a":0,"k":100},"lc":2,"lj":2,"ml":4,"w":{"a":0,"k":1.500},"c":{"a":0,"k":[0.059,0.047,0.024]}},{"ty":"tr","a":{"a":0,"k":[0,0]},"p":{"a":0,"k":[0,0]},"s":{"a":0,"k":[100,100]},"r":{"a":0,"k":0},"o":{"a":0,"k":100}}]},{"ty":"gr","nm":"path16","mn":"{89f20d03-d0ad-451d-82c3-f2f97c0e0428}","it":[{"ty":"sh","nm":"","mn":"{aad2a721-59e9-4102-ba68-11b7da36f89a}","d":1,"ks":{"a":0,"k":{"c":true,"v":[[-21.748,121.285],[-27.312,119.480],[-23.978,108.354],[-19.225,109.086],[-21.748,121.285]],"i":[[0,0],[2.965,0.943],[-1.331,2.501],[0,0],[0.116,-6.173]],"o":[[-1.537,-0.510],[0.790,-6.018],[2.649,0.021],[0,0],[0,0]]}}},{"ty":"fl","nm":"","mn":"{f9da37d8-7017-4de7-8c46-1285274bece1}","o":{"a":0,"k":100},"r":1,"c":{"a":0,"k":[1,0.929,0]}},{"ty":"st","nm":"","mn":"{3b94160d-b173-4ca6-ab18-0dcfcfcea08e}","o":{"a":0,"k":100},"lc":2,"lj":2,"ml":4,"w":{"a":0,"k":1.300},"c":{"a":0,"k":[0.059,0.047,0.024]}},{"ty":"tr","a":{"a":0,"k":[0,0]},"p":{"a":0,"k":[0,0]},"s":{"a":0,"k":[100,100]},"r":{"a":0,"k":0},"o":{"a":0,"k":100}}]},{"ty":"gr","nm":"path15","mn":"{5c05394a-9756-47f3-bacf-ca40ec7aa612}","it":[{"ty":"sh","nm":"","mn":"{9a7d0cef-4b52-4bf8-aaa1-dcd7c39c7573}","d":1,"ks":{"a":0,"k":{"c":true,"v":[[-20.913,135.164],[-28.486,130.206],[-27.833,121.139],[-21.343,123.384],[-20.913,135.164]],"i":[[0,0],[0,0],[-0.625,2.731],[-2.086,-0.376],[-1.011,-5.443]],"o":[[-3.612,-1.807],[-0.233,-2.772],[2.965,0.788],[-0.016,2.560],[0,0]]}}},{"ty":"fl","nm":"","mn":"{663e8b4e-2ef1-447d-aa21-297db15dd04d}","o":{"a":0,"k":100},"r":1,"c":{"a":0,"k":[1,0.929,0]}},{"ty":"st","nm":"","mn":"{1d48e1f3-56da-449c-8508-1eba0dbbaf4c}","o":{"a":0,"k":100},"lc":2,"lj":2,"ml":4,"w":{"a":0,"k":1.300},"c":{"a":0,"k":[0.059,0.047,0.024]}},{"ty":"tr","a":{"a":0,"k":[0,0]},"p":{"a":0,"k":[0,0]},"s":{"a":0,"k":[100,100]},"r":{"a":0,"k":0},"o":{"a":0,"k":100}}]},{"ty":"gr","nm":"path2","mn":"{37b035b6-679f-46f3-8f7b-318902eb900f}","it":[{"ty":"sh","nm":"","mn":"{579cff00-6f50-4d2a-a900-15ddf8d8e5ea}","d":1,"ks":{"a":0,"k":{"c":true,"v":[[-30.247,138.025],[-32.607,121.592],[-24.775,103.884],[-28.672,114.461],[-30.247,138.025]],"i":[[0,0],[0.041,5.477],[-3.751,4.529],[2.157,-5.762],[-0.772,-4.003]],"o":[[-2.129,-3.685],[-0.051,-6.749],[-0.826,3.391],[-2.157,5.762],[0,0]]}}},{"ty":"fl","nm":"","mn":"{fc80d093-07c7-486f-aa4c-180c95fc7e6d}","o":{"a":0,"k":100},"r":1,"c":{"a":0,"k":[1,0.929,0]}},{"ty":"st","nm":"","mn":"{644f462c-ad50-4ce0-bf96-bb1eb822316f}","o":{"a":0,"k":100},"lc":2,"lj":2,"ml":4,"w":{"a":0,"k":1.200},"c":{"a":0,"k":[0.059,0.047,0.024]}},{"ty":"tr","a":{"a":0,"k":[0,0]},"p":{"a":0,"k":[0,0]},"s":{"a":0,"k":[100,100]},"r":{"a":0,"k":0},"o":{"a":0,"k":100}}]},{"ty":"gr","nm":"background","mn":"{7a4743db-b962-4da1-9583-c4bd2a8fcc83}","it":[{"ty":"sh","nm":"","mn":"{11c433cd-2645-4ed1-bb7c-79583b1639b1}","d":1,"ks":{"a":0,"k":{"c":true,"v":[[-1.060,169.197],[-32.979,126.985],[1.927,99.018],[-6.549,128.793],[5.532,167.981],[-1.060,169.197]],"i":[[0,0],[-0.142,21.028],[-20.946,-8.535],[7.103,-6.814],[-8.745,-7.892],[0,0]],"o":[[-9.002,-14.578],[0.142,-21.028],[0,0],[1.222,15.935],[-5.504,1.626],[0,0]]}}},{"ty":"fl","nm":"","mn":"{5f8f3143-fe42-43a5-b0d8-33d07e18c530}","o":{"a":0,"k":100},"r":1,"c":{"a":0,"k":[0.984,0.976,0.976]}},{"ty":"st","nm":"","mn":"{dd42b27c-9125-4544-8b82-d4a4f689558d}","o":{"a":0,"k":95.686},"lc":2,"lj":2,"ml":4,"w":{"a":0,"k":0.200},"c":{"a":0,"k":[0.027,0.024,0.012]}},{"ty":"tr","a":{"a":0,"k":[0,0]},"p":{"a":0,"k":[0,0]},"s":{"a":0,"k":[100,100]},"r":{"a":0,"k":0},"o":{"a":0,"k":100}}]},{"ty":"tr","a":{"a":0,"k":[0,0]},"p":{"a":0,"k":[0,0]},"s":{"a":0,"k":[100,100]},"r":{"a":0,"k":0},"o":{"a":0,"k":100}}]},{"ty":"tr","a":{"a":0,"k":[0,0]},"p":{"a":0,"k":[70.293,-45.425]},"s":{"a":0,"k":[100,-100]},"r":{"a":0,"k":172.479},"o":{"a":0,"k":100}}]}]}],"meta":{"g":"Glaxnimate 0.5.4"}}